mirobody/__init__.py
mirobody/pub/agents/deep/README.md
mirobody/pub/agents/deep/exceptions/README.md
mirobody/pub/agents/deep/prompts/theta_health.jinja
mirobody/pub/agents/deep/prompts/theta_health_simple.jinja
mirobody/pub/agents/deep/prompts/theta_health_skills.jinja
mirobody/pub/htdoc/github-markdown-light.css
mirobody/pub/htdoc/index.html
mirobody/pub/htdoc/mirobody.svg
mirobody/pub/htdoc/__/auth/experiments.js
mirobody/pub/htdoc/__/auth/handler.js
mirobody/pub/htdoc/__/auth/iframe.js
mirobody/pub/htdoc/assets/index-CGbZCwPo.css
mirobody/pub/htdoc/assets/index-DHuBkmqT.js
mirobody/pub/htdoc/assets/index-giJ26_gF.css
mirobody/pub/htdoc/assets/index-hw4fOFph.js
mirobody/pub/htdoc/assets/index-legacy-BBuo6B4g.js
mirobody/pub/htdoc/assets/index-legacy-ClaqhAuh.js
mirobody/pub/htdoc/assets/logo-MLEW-e8g.svg
mirobody/pub/htdoc/assets/mcp_feature_eg-CcZqNkG5.png
mirobody/pub/htdoc/assets/mcp_feature_eg_cn-CFatLA2c.png
mirobody/pub/htdoc/assets/polyfills-legacy-9_J3MT5z.js
mirobody/pub/htdoc/assets/vital_epic-BzHLoQT_.svg
mirobody/pub/prompts/theta_health.jinja
mirobody/pub/resources/chart_url.html
mirobody/pub/resources/chart_url.json
mirobody/pub/resources/upload.html
mirobody/pub/resources/upload.json
mirobody/pub/tools/render-chart.js
mirobody/pub/tools/chart_schema/area.json
mirobody/pub/tools/chart_schema/bar.json
mirobody/pub/tools/chart_schema/boxplot.json
mirobody/pub/tools/chart_schema/column.json
mirobody/pub/tools/chart_schema/district-map.json
mirobody/pub/tools/chart_schema/dual-axes.json
mirobody/pub/tools/chart_schema/fishbone-diagram.json
mirobody/pub/tools/chart_schema/flow-diagram.json
mirobody/pub/tools/chart_schema/funnel.json
mirobody/pub/tools/chart_schema/histogram.json
mirobody/pub/tools/chart_schema/line.json
mirobody/pub/tools/chart_schema/liquid.json
mirobody/pub/tools/chart_schema/mind-map.json
mirobody/pub/tools/chart_schema/network-graph.json
mirobody/pub/tools/chart_schema/organization-chart.json
mirobody-1.0.3.dist-info/licenses/LICENSE
mirobody-1.0.3.dist-info/METADATA
mirobody-1.0.3.dist-info/WHEEL
mirobody-1.0.3.dist-info/top_level.txt
mirobody-1.0.3.dist-info/RECORD
