Metadata-Version: 2.4
Name: mirobody
Version: 1.0.3
Summary: Mirobody is a Python package for processing and analyzing health data.
Author-email: Theta AI Team <developer@thetahealth.ai>
Project-URL: Homepage, https://github.com/thetahealth/mirobody
Project-URL: Bug Reports, https://github.com/thetahealth/mirobody/issues
Project-URL: Source, https://github.com/thetahealth/mirobody
Keywords: health,wellness,data processing,AI,LLM
Classifier: Development Status :: 4 - Beta
Classifier: Intended Audience :: Developers
Classifier: Programming Language :: Python :: 3
Classifier: Programming Language :: Python :: 3.10
Classifier: Programming Language :: Python :: 3.11
Classifier: Programming Language :: Python :: 3.12
Requires-Python: >=3.8
License-File: LICENSE
Requires-Dist: setuptools
Requires-Dist: python-dotenv
Requires-Dist: ruamel.yaml<0.18.0
Requires-Dist: cryptography
Requires-Dist: redis
Requires-Dist: psycopg[binary]
Requires-Dist: psycopg[pool]
Requires-Dist: sqlalchemy
Requires-Dist: pandas
Requires-Dist: aiohttp
Requires-Dist: starlette
Requires-Dist: fastapi
Requires-Dist: uvicorn
Requires-Dist: pydantic
Requires-Dist: pyjwt
Requires-Dist: pytz
Requires-Dist: aioboto3
Requires-Dist: cachetools
Requires-Dist: pypdf>=5.1.0
Requires-Dist: pypdfium2>=4.30.0
Requires-Dist: pdfplumber~=0.11.7
Requires-Dist: Pillow<12.0.0,>=11.1.0
Requires-Dist: tinytag>=1.6.0
Requires-Dist: mutagen~=1.47.0
Requires-Dist: rarfile~=4.0
Requires-Dist: py7zr~=0.22.0
Requires-Dist: openpyxl~=3.1.5
Requires-Dist: mandrill
Requires-Dist: openai>=2.11.0
Requires-Dist: openai-agents
Requires-Dist: google-genai
Requires-Dist: volcengine-python-sdk[ark]~=3.0.1
Requires-Dist: langchain
Requires-Dist: langchain-openai
Requires-Dist: langchain-anthropic
Requires-Dist: langchain-google-genai>=4.1.2
Requires-Dist: langchain-google-vertexai
Requires-Dist: langchain_community
Requires-Dist: deepagents
Requires-Dist: jinja2
Requires-Dist: dashscope
Requires-Dist: aiofiles~=24.1.0
Requires-Dist: oss2
Requires-Dist: pycryptodome>=3.20.0
Requires-Dist: requests-oauthlib
Requires-Dist: tiktoken>=0.9.0
Dynamic: license-file
